temp_class.py
dsfsgdf-1.0.5.dist-info/METADATA
dsfsgdf-1.0.5.dist-info/WHEEL
dsfsgdf-1.0.5.dist-info/top_level.txt
dsfsgdf-1.0.5.dist-info/RECORD
