Metadata-Version: 2.1
Name: dsfsgdf
Version: 1.0.5
Summary: temp class
Home-page: UNKNOWN
Author: UNKNOWN
Author-email: UNKNOWN
License: UNKNOWN
Platform: UNKNOWN
Requires-Dist: boto3 (>=1.2)
